{
    "minimumVersion": 1,
    "packages": [
        {
            "name": "Light Modpack",
            "title": "Light Modpack",
            "version": "20100223",
            "location": "lightpack.json",
            "priority": 1
        },
        {
            "name": "Monster Modpack",
            "title": "Monster Modpack",
            "version": "20100223",
            "location": "monsterpack.json",
            "priority": 1
        },
		{
			"name" : "RoE Modpack",
			"version" : "2016-11-27-17-48-08",
			"location" : "roe-modpack.json",
			"priority" : 0
		}
    ]
}